{
  "balcaro" : {
    "nombre" : "Rodrigo",
    "apellido" : "Balcabao",
    "username" : "balcaro",
    "password" : "rodri123",
    "email" : "rodddde@gmail.com",
    "genero" : "M",
    "rol" : 0
  },
  "viyi" : {
    "nombre" : "Virginia",
    "apellido" : "Perez",
    "username" : "viyi",
    "password" : "viyi123",
    "email" : "virginia@gmail.com",
    "genero" : "F",
    "rol" : 0
  },
  "Oti" : {
    "nombre" : "Octavio",
    "apellido" : "Lopez",
    "username" : "Oti",
    "password" : "Lopez1503",
    "email" : "lopezortizoctavio@gmail.com",
    "genero" : "M",
    "rol" : 1
  },
  "pruper" : {
    "nombre" : "Pablo",
    "apellido" : "Ruper",
    "username" : "pruper",
    "password" : "prupppper123",
    "email" : "ssssaaaa@gmail.com",
    "genero" : "M",
    "rol" : 0
  },
  "robertLaz" : {
    "nombre" : "Roberto",
    "apellido" : "Lazaro",
    "username" : "robertLaz",
    "password" : "robert123",
    "email" : "rlazaro@gmail.com",
    "genero" : "M",
    "rol" : 0
  },
  "juli" : {
    "nombre" : "Julian",
    "apellido" : "Dunand",
    "username" : "juli",
    "password" : "julidd123",
    "email" : "juli@gmail.com",
    "genero" : "M",
    "rol" : 0
  },
  "francis" : {
    "nombre" : "Francisco",
    "apellido" : "Bueno",
    "username" : "francis",
    "password" : "francis123",
    "email" : "frandrane@gmail.com",
    "genero" : "M",
    "rol" : 0
  },
  "ezequiel" : {
    "nombre" : "Ezequiel",
    "apellido" : "Gimenez",
    "username" : "ezequiel",
    "password" : "ezequiel123",
    "email" : "ezeeze@gmail.com",
    "genero" : "M",
    "rol" : 0
  },
  "florcita" : {
    "nombre" : "Florencia",
    "apellido" : "Rodriguez",
    "username" : "florcita",
    "password" : "flor123",
    "email" : "florcita@gmail.com",
    "genero" : "F",
    "rol" : 0
  },
  "juliaGonza" : {
    "nombre" : "Julia",
    "apellido" : "Gonzalez",
    "username" : "juliaGonza",
    "password" : "gonzalesjulia123",
    "email" : "pepegrillo@gmail.com",
    "genero" : "F",
    "rol" : 0
  },
  "Naza1991" : {
    "nombre" : "Nazareno",
    "apellido" : "Pisoni",
    "username" : "Naza1991",
    "password" : "NazaPisoni91!!",
    "email" : "nazareno_pisoni@hotmail.com",
    "genero" : "M",
    "rol" : 0
  }
}